aql_builder/__init__.py
aql_builder/assumptions.py
aql_builder/errors.py
aql_builder/types.py
aql_builder-0.0.14.dist-info/LICENSE.txt
aql_builder-0.0.14.dist-info/METADATA
aql_builder-0.0.14.dist-info/WHEEL
aql_builder-0.0.14.dist-info/top_level.txt
aql_builder-0.0.14.dist-info/RECORD
