Metadata-Version: 2.1
Name: aql-builder
Version: 0.0.14
Summary: ArangoDB AQL builder
Maintainer-email: Aqua Penguin <aqua.penguin.34@gmail.com>
License:                                  Apache License
Project-URL: Homepage, https://foss.heptapod.net/aquapenguin/aql-builder
Project-URL: Source, https://foss.heptapod.net/aquapenguin/aql-builder/-/tree/branch/default
Project-URL: Tracker, https://foss.heptapod.net/aquapenguin/aql-builder/-/issues
Keywords: aql,builder
Classifier: License :: OSI Approved :: Apache Software License
Classifier: Operating System :: OS Independent
Classifier: Programming Language :: Python
Classifier: Programming Language :: Python :: 3
Classifier: Programming Language :: Python :: 3.7
Classifier: Programming Language :: Python :: 3.8
Classifier: Programming Language :: Python :: 3.9
Classifier: Programming Language :: Python :: 3.10
Classifier: Programming Language :: Python :: 3.11
Requires-Python: >=3.7
License-File: LICENSE.txt
